{
  "funcionarios": [
    {
      "id": 1,
      "nome": "Reginaldo",
      "cargo": "Programador",
      "equipamento": {
        "id": 1,
        "tipo": "Mac",
        "so": "Mac OS"
      }
    },
    {
      "id": 2,
      "nome": "Gabriel",
      "cargo": "Programador",
      "equipamento": {
        "id": 2,
        "tipo": "Thinkpad",
        "so": "Windows"
      }
    },
    {
      "nome": "Mais um",
      "cargo": "Eu alterei o cargo",
      "id": 4,
      "equipamento": {
        "id": 2,
        "tipo": "Thinkpad",
        "so": "Windows"
      }
    }
  ],
  "equipamentos": [
    {
      "id": 1,
      "tipo": "Mac",
      "SO": "IOS",
      "func_id": 1
    },
    {
      "id": 2,
      "tipo": "Thinkpad",
      "SO": "Windows",
      "func_id": 2
    }
  ]
}